[
{"pref":"北海道","name":"札幌市","empty":"125,400"},
{"pref":"北海道","name":"函館市","empty":"24,460"},
{"pref":"北海道","name":"小樽市","empty":"11,200"},
{"pref":"北海道","name":"旭川市","empty":"21,920"},
{"pref":"北海道","name":"室蘭市","empty":"8,960"},
{"pref":"北海道","name":"釧路市","empty":"13,740"},
{"pref":"北海道","name":"帯広市","empty":"10,290"},
{"pref":"北海道","name":"北見市","empty":"8,590"},
{"pref":"北海道","name":"夕張市","empty":"2,680"},
{"pref":"北海道","name":"岩見沢市","empty":"5,260"},
{"pref":"北海道","name":"網走市","empty":"2,500"},
{"pref":"北海道","name":"留萌市","empty":"2,310"},
{"pref":"北海道","name":"苫小牧市","empty":"13,120"},
{"pref":"北海道","name":"稚内市","empty":"2,690"},
{"pref":"北海道","name":"美唄市","empty":"2,120"},
{"pref":"北海道","name":"芦別市","empty":"2,250"},
{"pref":"北海道","name":"江別市","empty":"5,410"},
{"pref":"北海道","name":"赤平市","empty":"1,660"},
{"pref":"北海道","name":"紋別市","empty":"1,940"},
{"pref":"北海道","name":"士別市","empty":"1,350"},
{"pref":"北海道","name":"名寄市","empty":"2,020"},
{"pref":"北海道","name":"三笠市","empty":"1,950"},
{"pref":"北海道","name":"根室市","empty":"1,770"},
{"pref":"北海道","name":"千歳市","empty":"6,250"},
{"pref":"北海道","name":"滝川市","empty":"3,300"},
{"pref":"北海道","name":"砂川市","empty":"1,140"},
{"pref":"北海道","name":"歌志内市","empty":"730"},
{"pref":"北海道","name":"深川市","empty":"1,670"},
{"pref":"北海道","name":"富良野市","empty":"1,230"},
{"pref":"北海道","name":"登別市","empty":"3,750"},
{"pref":"北海道","name":"恵庭市","empty":"4,070"},
{"pref":"北海道","name":"伊達市","empty":"2,120"},
{"pref":"北海道","name":"北広島市","empty":"1,670"},
{"pref":"北海道","name":"石狩市","empty":"2,790"},
{"pref":"北海道","name":"北斗市","empty":"2,680"},
{"pref":"青森","name":"青森市","empty":"19,700"},
{"pref":"青森","name":"弘前市","empty":"11,650"},
{"pref":"青森","name":"八戸市","empty":"16,970"},
{"pref":"青森","name":"黒石市","empty":"1,800"},
{"pref":"青森","name":"五所川原市","empty":"4,020"},
{"pref":"青森","name":"十和田市","empty":"4,830"},
{"pref":"青森","name":"三沢市","empty":"3,240"},
{"pref":"青森","name":"むつ市","empty":"5,430"},
{"pref":"青森","name":"つがる市","empty":"1,710"},
{"pref":"青森","name":"平川市","empty":"1,400"},
{"pref":"岩手","name":"盛岡市","empty":"21,990"},
{"pref":"岩手","name":"宮古市","empty":"3,650"},
{"pref":"岩手","name":"大船渡市","empty":"2,450"},
{"pref":"岩手","name":"花巻市","empty":"5,270"},
{"pref":"岩手","name":"北上市","empty":"7,360"},
{"pref":"岩手","name":"久慈市","empty":"3,210"},
{"pref":"岩手","name":"遠野市","empty":"2,160"},
{"pref":"岩手","name":"一関市","empty":"7,640"},
{"pref":"岩手","name":"陸前高田市","empty":"1,960"},
{"pref":"岩手","name":"釜石市","empty":"4,520"},
{"pref":"岩手","name":"二戸市","empty":"2,440"},
{"pref":"岩手","name":"八幡平市","empty":"3,040"},
{"pref":"岩手","name":"奥州市","empty":"7,320"},
{"pref":"岩手","name":"滝沢市","empty":"2,460"},
{"pref":"宮城","name":"仙台市","empty":"63,800"},
{"pref":"宮城","name":"石巻市","empty":"13,410"},
{"pref":"宮城","name":"塩竈市","empty":"2,590"},
{"pref":"宮城","name":"気仙沼市","empty":"5,210"},
{"pref":"宮城","name":"白石市","empty":"2,200"},
{"pref":"宮城","name":"名取市","empty":"3,550"},
{"pref":"宮城","name":"角田市","empty":"1,490"},
{"pref":"宮城","name":"多賀城市","empty":"2,570"},
{"pref":"宮城","name":"岩沼市","empty":"2,010"},
{"pref":"宮城","name":"登米市","empty":"3,390"},
{"pref":"宮城","name":"栗原市","empty":"3,240"},
{"pref":"宮城","name":"東松島市","empty":"2,020"},
{"pref":"宮城","name":"大崎市","empty":"7,750"},
{"pref":"宮城","name":"富谷市","empty":"920"},
{"pref":"秋田","name":"秋田市","empty":"20,840"},
{"pref":"秋田","name":"能代市","empty":"4,630"},
{"pref":"秋田","name":"横手市","empty":"4,100"},
{"pref":"秋田","name":"大館市","empty":"4,400"},
{"pref":"秋田","name":"男鹿市","empty":"2,640"},
{"pref":"秋田","name":"湯沢市","empty":"2,080"},
{"pref":"秋田","name":"鹿角市","empty":"2,360"},
{"pref":"秋田","name":"由利本荘市","empty":"3,960"},
{"pref":"秋田","name":"潟上市","empty":"1,530"},
{"pref":"秋田","name":"大仙市","empty":"3,440"},
{"pref":"秋田","name":"北秋田市","empty":"2,280"},
{"pref":"秋田","name":"にかほ市","empty":"1,430"},
{"pref":"秋田","name":"仙北市","empty":"1,710"},
{"pref":"山形","name":"山形市","empty":"14,460"},
{"pref":"山形","name":"米沢市","empty":"5,270"},
{"pref":"山形","name":"鶴岡市","empty":"7,050"},
{"pref":"山形","name":"酒田市","empty":"6,220"},
{"pref":"山形","name":"新庄市","empty":"1,690"},
{"pref":"山形","name":"寒河江市","empty":"1,520"},
{"pref":"山形","name":"上山市","empty":"1,830"},
{"pref":"山形","name":"村山市","empty":"780"},
{"pref":"山形","name":"長井市","empty":"1,160"},
{"pref":"山形","name":"天童市","empty":"2,650"},
{"pref":"山形","name":"東根市","empty":"1,940"},
{"pref":"山形","name":"尾花沢市","empty":"620"},
{"pref":"山形","name":"南陽市","empty":"1,540"},
{"pref":"福島","name":"福島市","empty":"17,070"},
{"pref":"福島","name":"会津若松市","empty":"8,690"},
{"pref":"福島","name":"郡山市","empty":"24,010"},
{"pref":"福島","name":"いわき市","empty":"19,680"},
{"pref":"福島","name":"白河市","empty":"3,560"},
{"pref":"福島","name":"須賀川市","empty":"2,960"},
{"pref":"福島","name":"喜多方市","empty":"3,950"},
{"pref":"福島","name":"相馬市","empty":"2,910"},
{"pref":"福島","name":"二本松市","empty":"3,190"},
{"pref":"福島","name":"田村市","empty":"1,490"},
{"pref":"福島","name":"南相馬市","empty":"7,960"},
{"pref":"福島","name":"伊達市","empty":"2,630"},
{"pref":"福島","name":"本宮市","empty":"1,250"},
{"pref":"茨城","name":"水戸市","empty":"22,130"},
{"pref":"茨城","name":"日立市","empty":"15,640"},
{"pref":"茨城","name":"土浦市","empty":"10,830"},
{"pref":"茨城","name":"古河市","empty":"8,280"},
{"pref":"茨城","name":"石岡市","empty":"5,280"},
{"pref":"茨城","name":"結城市","empty":"2,380"},
{"pref":"茨城","name":"龍ケ崎市","empty":"5,050"},
{"pref":"茨城","name":"下妻市","empty":"2,810"},
{"pref":"茨城","name":"常総市","empty":"3,050"},
{"pref":"茨城","name":"常陸太田市","empty":"2,930"},
{"pref":"茨城","name":"高萩市","empty":"2,480"},
{"pref":"茨城","name":"北茨城市","empty":"3,180"},
{"pref":"茨城","name":"笠間市","empty":"4,650"},
{"pref":"茨城","name":"取手市","empty":"8,280"},
{"pref":"茨城","name":"牛久市","empty":"4,220"},
{"pref":"茨城","name":"つくば市","empty":"18,740"},
{"pref":"茨城","name":"ひたちなか市","empty":"8,620"},
{"pref":"茨城","name":"鹿嶋市","empty":"7,280"},
{"pref":"茨城","name":"潮来市","empty":"2,050"},
{"pref":"茨城","name":"守谷市","empty":"2,510"},
{"pref":"茨城","name":"常陸大宮市","empty":"2,980"},
{"pref":"茨城","name":"那珂市","empty":"2,470"},
{"pref":"茨城","name":"筑西市","empty":"6,950"},
{"pref":"茨城","name":"坂東市","empty":"2,400"},
{"pref":"茨城","name":"稲敷市","empty":"2,350"},
{"pref":"茨城","name":"かすみがうら市","empty":"2,220"},
{"pref":"茨城","name":"桜川市","empty":"1,980"},
{"pref":"茨城","name":"神栖市","empty":"8,660"},
{"pref":"茨城","name":"行方市","empty":"1,310"},
{"pref":"茨城","name":"鉾田市","empty":"4,450"},
{"pref":"茨城","name":"つくばみらい市","empty":"1,780"},
{"pref":"茨城","name":"小美玉市","empty":"2,920"},
{"pref":"栃木","name":"宇都宮市","empty":"44,410"},
{"pref":"栃木","name":"足利市","empty":"14,520"},
{"pref":"栃木","name":"栃木市","empty":"9,580"},
{"pref":"栃木","name":"佐野市","empty":"9,840"},
{"pref":"栃木","name":"鹿沼市","empty":"6,010"},
{"pref":"栃木","name":"日光市","empty":"9,830"},
{"pref":"栃木","name":"小山市","empty":"11,450"},
{"pref":"栃木","name":"真岡市","empty":"4,370"},
{"pref":"栃木","name":"大田原市","empty":"4,910"},
{"pref":"栃木","name":"矢板市","empty":"3,210"},
{"pref":"栃木","name":"那須塩原市","empty":"11,310"},
{"pref":"栃木","name":"さくら市","empty":"2,730"},
{"pref":"栃木","name":"那須烏山市","empty":"1,840"},
{"pref":"栃木","name":"下野市","empty":"3,660"},
{"pref":"群馬","name":"前橋市","empty":"26,340"},
{"pref":"群馬","name":"高崎市","empty":"27,910"},
{"pref":"群馬","name":"桐生市","empty":"13,170"},
{"pref":"群馬","name":"伊勢崎市","empty":"13,150"},
{"pref":"群馬","name":"太田市","empty":"14,010"},
{"pref":"群馬","name":"沼田市","empty":"4,120"},
{"pref":"群馬","name":"館林市","empty":"6,060"},
{"pref":"群馬","name":"渋川市","empty":"6,000"},
{"pref":"群馬","name":"藤岡市","empty":"3,890"},
{"pref":"群馬","name":"富岡市","empty":"3,140"},
{"pref":"群馬","name":"安中市","empty":"4,900"},
{"pref":"群馬","name":"みどり市","empty":"3,730"},
{"pref":"埼玉","name":"さいたま市","empty":"57,500"},
{"pref":"埼玉","name":"川越市","empty":"14,940"},
{"pref":"埼玉","name":"熊谷市","empty":"11,720"},
{"pref":"埼玉","name":"川口市","empty":"29,150"},
{"pref":"埼玉","name":"行田市","empty":"4,930"},
{"pref":"埼玉","name":"秩父市","empty":"5,880"},
{"pref":"埼玉","name":"所沢市","empty":"16,860"},
{"pref":"埼玉","name":"飯能市","empty":"4,790"},
{"pref":"埼玉","name":"加須市","empty":"5,100"},
{"pref":"埼玉","name":"本庄市","empty":"5,440"},
{"pref":"埼玉","name":"東松山市","empty":"5,770"},
{"pref":"埼玉","name":"春日部市","empty":"9,490"},
{"pref":"埼玉","name":"狭山市","empty":"7,650"},
{"pref":"埼玉","name":"羽生市","empty":"2,940"},
{"pref":"埼玉","name":"鴻巣市","empty":"5,970"},
{"pref":"埼玉","name":"深谷市","empty":"8,580"},
{"pref":"埼玉","name":"上尾市","empty":"9,370"},
{"pref":"埼玉","name":"草加市","empty":"10,660"},
{"pref":"埼玉","name":"越谷市","empty":"12,000"},
{"pref":"埼玉","name":"蕨市","empty":"4,670"},
{"pref":"埼玉","name":"戸田市","empty":"5,410"},
{"pref":"埼玉","name":"入間市","empty":"4,900"},
{"pref":"埼玉","name":"朝霞市","empty":"6,250"},
{"pref":"埼玉","name":"志木市","empty":"3,280"},
{"pref":"埼玉","name":"和光市","empty":"3,570"},
{"pref":"埼玉","name":"新座市","empty":"6,160"},
{"pref":"埼玉","name":"桶川市","empty":"2,830"},
{"pref":"埼玉","name":"久喜市","empty":"7,060"},
{"pref":"埼玉","name":"北本市","empty":"3,390"},
{"pref":"埼玉","name":"八潮市","empty":"3,770"},
{"pref":"埼玉","name":"富士見市","empty":"5,300"},
{"pref":"埼玉","name":"三郷市","empty":"5,090"},
{"pref":"埼玉","name":"蓮田市","empty":"2,240"},
{"pref":"埼玉","name":"坂戸市","empty":"6,200"},
{"pref":"埼玉","name":"幸手市","empty":"2,380"},
{"pref":"埼玉","name":"鶴ヶ島市","empty":"3,790"},
{"pref":"埼玉","name":"日高市","empty":"2,230"},
{"pref":"埼玉","name":"吉川市","empty":"1,780"},
{"pref":"埼玉","name":"ふじみ野市","empty":"6,570"},
{"pref":"埼玉","name":"白岡市","empty":"1,540"},
{"pref":"千葉","name":"千葉市","empty":"57,900"},
{"pref":"千葉","name":"銚子市","empty":"5,680"},
{"pref":"千葉","name":"市川市","empty":"29,640"},
{"pref":"千葉","name":"船橋市","empty":"32,120"},
{"pref":"千葉","name":"館山市","empty":"7,450"},
{"pref":"千葉","name":"木更津市","empty":"9,240"},
{"pref":"千葉","name":"松戸市","empty":"32,250"},
{"pref":"千葉","name":"野田市","empty":"7,040"},
{"pref":"千葉","name":"茂原市","empty":"8,710"},
{"pref":"千葉","name":"成田市","empty":"7,730"},
{"pref":"千葉","name":"佐倉市","empty":"7,090"},
{"pref":"千葉","name":"東金市","empty":"5,230"},
{"pref":"千葉","name":"旭市","empty":"3,610"},
{"pref":"千葉","name":"習志野市","empty":"9,010"},
{"pref":"千葉","name":"柏市","empty":"22,860"},
{"pref":"千葉","name":"勝浦市","empty":"6,800"},
{"pref":"千葉","name":"市原市","empty":"18,680"},
{"pref":"千葉","name":"流山市","empty":"7,420"},
{"pref":"千葉","name":"八千代市","empty":"9,140"},
{"pref":"千葉","name":"我孫子市","empty":"6,210"},
{"pref":"千葉","name":"鴨川市","empty":"5,630"},
{"pref":"千葉","name":"鎌ケ谷市","empty":"4,730"},
{"pref":"千葉","name":"君津市","empty":"6,050"},
{"pref":"千葉","name":"富津市","empty":"3,610"},
{"pref":"千葉","name":"浦安市","empty":"9,110"},
{"pref":"千葉","name":"四街道市","empty":"3,050"},
{"pref":"千葉","name":"袖ケ浦市","empty":"2,520"},
{"pref":"千葉","name":"八街市","empty":"3,970"},
{"pref":"千葉","name":"印西市","empty":"3,620"},
{"pref":"千葉","name":"白井市","empty":"1,860"},
{"pref":"千葉","name":"富里市","empty":"2,670"},
{"pref":"千葉","name":"南房総市","empty":"5,300"},
{"pref":"千葉","name":"匝瑳市","empty":"2,180"},
{"pref":"千葉","name":"香取市","empty":"4,540"},
{"pref":"千葉","name":"山武市","empty":"4,070"},
{"pref":"千葉","name":"いすみ市","empty":"5,360"},
{"pref":"千葉","name":"大網白里市","empty":"3,690"},
{"pref":"東京","name":"八王子市","empty":"35,170"},
{"pref":"東京","name":"立川市","empty":"11,090"},
{"pref":"東京","name":"武蔵野市","empty":"9,080"},
{"pref":"東京","name":"三鷹市","empty":"10,730"},
{"pref":"東京","name":"青梅市","empty":"6,900"},
{"pref":"東京","name":"府中市","empty":"15,030"},
{"pref":"東京","name":"昭島市","empty":"7,530"},
{"pref":"東京","name":"調布市","empty":"12,690"},
{"pref":"東京","name":"町田市","empty":"20,010"},
{"pref":"東京","name":"小金井市","empty":"6,940"},
{"pref":"東京","name":"小平市","empty":"12,960"},
{"pref":"東京","name":"日野市","empty":"9,760"},
{"pref":"東京","name":"東村山市","empty":"7,090"},
{"pref":"東京","name":"国分寺市","empty":"6,970"},
{"pref":"東京","name":"国立市","empty":"5,950"},
{"pref":"東京","name":"福生市","empty":"3,410"},
{"pref":"東京","name":"狛江市","empty":"4,190"},
{"pref":"東京","name":"東大和市","empty":"3,780"},
{"pref":"東京","name":"清瀬市","empty":"3,710"},
{"pref":"東京","name":"東久留米市","empty":"6,050"},
{"pref":"東京","name":"武蔵村山市","empty":"3,650"},
{"pref":"東京","name":"多摩市","empty":"7,900"},
{"pref":"東京","name":"稲城市","empty":"3,570"},
{"pref":"東京","name":"羽村市","empty":"3,010"},
{"pref":"東京","name":"あきる野市","empty":"3,520"},
{"pref":"東京","name":"西東京市","empty":"8,690"},
{"pref":"神奈川","name":"横浜市","empty":"178,300"},
{"pref":"神奈川","name":"川崎市","empty":"73,800"},
{"pref":"神奈川","name":"相模原市","empty":"36,200"},
{"pref":"神奈川","name":"横須賀市","empty":"28,750"},
{"pref":"神奈川","name":"平塚市","empty":"13,770"},
{"pref":"神奈川","name":"鎌倉市","empty":"9,460"},
{"pref":"神奈川","name":"藤沢市","empty":"22,410"},
{"pref":"神奈川","name":"小田原市","empty":"13,350"},
{"pref":"神奈川","name":"茅ヶ崎市","empty":"9,270"},
{"pref":"神奈川","name":"逗子市","empty":"5,020"},
{"pref":"神奈川","name":"三浦市","empty":"4,850"},
{"pref":"神奈川","name":"秦野市","empty":"10,170"},
{"pref":"神奈川","name":"厚木市","empty":"15,450"},
{"pref":"神奈川","name":"大和市","empty":"14,660"},
{"pref":"神奈川","name":"伊勢原市","empty":"7,010"},
{"pref":"神奈川","name":"海老名市","empty":"4,770"},
{"pref":"神奈川","name":"座間市","empty":"7,190"},
{"pref":"神奈川","name":"南足柄市","empty":"1,960"},
{"pref":"神奈川","name":"綾瀬市","empty":"2,850"},
{"pref":"新潟","name":"新潟市","empty":"48,400"},
{"pref":"新潟","name":"長岡市","empty":"14,330"},
{"pref":"新潟","name":"三条市","empty":"4,450"},
{"pref":"新潟","name":"柏崎市","empty":"6,810"},
{"pref":"新潟","name":"新発田市","empty":"4,990"},
{"pref":"新潟","name":"小千谷市","empty":"1,530"},
{"pref":"新潟","name":"加茂市","empty":"1,520"},
{"pref":"新潟","name":"十日町市","empty":"2,340"},
{"pref":"新潟","name":"見附市","empty":"1,130"},
{"pref":"新潟","name":"村上市","empty":"4,570"},
{"pref":"新潟","name":"燕市","empty":"3,790"},
{"pref":"新潟","name":"糸魚川市","empty":"3,360"},
{"pref":"新潟","name":"妙高市","empty":"2,510"},
{"pref":"新潟","name":"五泉市","empty":"2,030"},
{"pref":"新潟","name":"上越市","empty":"10,830"},
{"pref":"新潟","name":"阿賀野市","empty":"1,790"},
{"pref":"新潟","name":"佐渡市","empty":"7,300"},
{"pref":"新潟","name":"魚沼市","empty":"1,670"},
{"pref":"新潟","name":"南魚沼市","empty":"2,050"},
{"pref":"新潟","name":"胎内市","empty":"1,960"},
{"pref":"富山","name":"富山市","empty":"24,230"},
{"pref":"富山","name":"高岡市","empty":"11,080"},
{"pref":"富山","name":"魚津市","empty":"4,120"},
{"pref":"富山","name":"氷見市","empty":"2,550"},
{"pref":"富山","name":"滑川市","empty":"1,650"},
{"pref":"富山","name":"黒部市","empty":"2,680"},
{"pref":"富山","name":"砺波市","empty":"1,940"},
{"pref":"富山","name":"小矢部市","empty":"1,340"},
{"pref":"富山","name":"南砺市","empty":"2,210"},
{"pref":"富山","name":"射水市","empty":"4,110"},
{"pref":"石川","name":"金沢市","empty":"33,750"},
{"pref":"石川","name":"七尾市","empty":"4,790"},
{"pref":"石川","name":"小松市","empty":"5,250"},
{"pref":"石川","name":"輪島市","empty":"3,120"},
{"pref":"石川","name":"珠洲市","empty":"1,480"},
{"pref":"石川","name":"加賀市","empty":"6,140"},
{"pref":"石川","name":"羽咋市","empty":"1,700"},
{"pref":"石川","name":"かほく市","empty":"990"},
{"pref":"石川","name":"白山市","empty":"4,190"},
{"pref":"石川","name":"能美市","empty":"1,760"},
{"pref":"石川","name":"野々市市","empty":"3,500"},
{"pref":"福井","name":"福井市","empty":"17,020"},
{"pref":"福井","name":"敦賀市","empty":"4,890"},
{"pref":"福井","name":"小浜市","empty":"2,740"},
{"pref":"福井","name":"大野市","empty":"1,390"},
{"pref":"福井","name":"勝山市","empty":"1,190"},
{"pref":"福井","name":"鯖江市","empty":"2,550"},
{"pref":"福井","name":"あわら市","empty":"2,000"},
{"pref":"福井","name":"越前市","empty":"4,460"},
{"pref":"福井","name":"坂井市","empty":"4,170"},
{"pref":"山梨","name":"甲府市","empty":"22,730"},
{"pref":"山梨","name":"富士吉田市","empty":"3,120"},
{"pref":"山梨","name":"都留市","empty":"2,460"},
{"pref":"山梨","name":"山梨市","empty":"2,900"},
{"pref":"山梨","name":"大月市","empty":"2,200"},
{"pref":"山梨","name":"韮崎市","empty":"2,770"},
{"pref":"山梨","name":"南アルプス市","empty":"4,510"},
{"pref":"山梨","name":"北杜市","empty":"14,230"},
{"pref":"山梨","name":"甲斐市","empty":"5,140"},
{"pref":"山梨","name":"笛吹市","empty":"7,080"},
{"pref":"山梨","name":"上野原市","empty":"2,500"},
{"pref":"山梨","name":"甲州市","empty":"2,360"},
{"pref":"山梨","name":"中央市","empty":"2,360"},
{"pref":"長野","name":"長野市","empty":"27,750"},
{"pref":"長野","name":"松本市","empty":"18,620"},
{"pref":"長野","name":"上田市","empty":"13,060"},
{"pref":"長野","name":"岡谷市","empty":"3,920"},
{"pref":"長野","name":"飯田市","empty":"7,040"},
{"pref":"長野","name":"諏訪市","empty":"5,960"},
{"pref":"長野","name":"須坂市","empty":"3,120"},
{"pref":"長野","name":"小諸市","empty":"4,290"},
{"pref":"長野","name":"伊那市","empty":"5,860"},
{"pref":"長野","name":"駒ヶ根市","empty":"2,350"},
{"pref":"長野","name":"中野市","empty":"1,700"},
{"pref":"長野","name":"大町市","empty":"3,450"},
{"pref":"長野","name":"飯山市","empty":"1,220"},
{"pref":"長野","name":"茅野市","empty":"13,500"},
{"pref":"長野","name":"塩尻市","empty":"4,070"},
{"pref":"長野","name":"佐久市","empty":"9,500"},
{"pref":"長野","name":"千曲市","empty":"4,530"},
{"pref":"長野","name":"東御市","empty":"2,080"},
{"pref":"長野","name":"安曇野市","empty":"6,020"},
{"pref":"岐阜","name":"岐阜市","empty":"39,040"},
{"pref":"岐阜","name":"大垣市","empty":"11,460"},
{"pref":"岐阜","name":"高山市","empty":"7,790"},
{"pref":"岐阜","name":"多治見市","empty":"6,740"},
{"pref":"岐阜","name":"関市","empty":"5,430"},
{"pref":"岐阜","name":"中津川市","empty":"5,000"},
{"pref":"岐阜","name":"美濃市","empty":"1,280"},
{"pref":"岐阜","name":"瑞浪市","empty":"2,700"},
{"pref":"岐阜","name":"羽島市","empty":"2,940"},
{"pref":"岐阜","name":"恵那市","empty":"3,420"},
{"pref":"岐阜","name":"美濃加茂市","empty":"4,210"},
{"pref":"岐阜","name":"土岐市","empty":"3,350"},
{"pref":"岐阜","name":"各務原市","empty":"8,300"},
{"pref":"岐阜","name":"可児市","empty":"4,200"},
{"pref":"岐阜","name":"山県市","empty":"1,860"},
{"pref":"岐阜","name":"瑞穂市","empty":"3,220"},
{"pref":"岐阜","name":"飛騨市","empty":"1,830"},
{"pref":"岐阜","name":"本巣市","empty":"1,750"},
{"pref":"岐阜","name":"郡上市","empty":"3,950"},
{"pref":"岐阜","name":"下呂市","empty":"2,780"},
{"pref":"岐阜","name":"海津市","empty":"1,350"},
{"pref":"静岡","name":"静岡市","empty":"47,900"},
{"pref":"静岡","name":"浜松市","empty":"46,700"},
{"pref":"静岡","name":"沼津市","empty":"15,050"},
{"pref":"静岡","name":"熱海市","empty":"20,360"},
{"pref":"静岡","name":"三島市","empty":"7,570"},
{"pref":"静岡","name":"富士宮市","empty":"6,510"},
{"pref":"静岡","name":"伊東市","empty":"19,750"},
{"pref":"静岡","name":"島田市","empty":"4,430"},
{"pref":"静岡","name":"富士市","empty":"14,410"},
{"pref":"静岡","name":"磐田市","empty":"8,500"},
{"pref":"静岡","name":"焼津市","empty":"7,140"},
{"pref":"静岡","name":"掛川市","empty":"6,340"},
{"pref":"静岡","name":"藤枝市","empty":"6,980"},
{"pref":"静岡","name":"御殿場市","empty":"6,350"},
{"pref":"静岡","name":"袋井市","empty":"6,130"},
{"pref":"静岡","name":"下田市","empty":"3,940"},
{"pref":"静岡","name":"裾野市","empty":"4,160"},
{"pref":"静岡","name":"湖西市","empty":"3,520"},
{"pref":"静岡","name":"伊豆市","empty":"6,710"},
{"pref":"静岡","name":"御前崎市","empty":"2,420"},
{"pref":"静岡","name":"菊川市","empty":"3,020"},
{"pref":"静岡","name":"伊豆の国市","empty":"6,730"},
{"pref":"静岡","name":"牧之原市","empty":"3,260"},
{"pref":"愛知","name":"名古屋市","empty":"156,900"},
{"pref":"愛知","name":"豊橋市","empty":"21,510"},
{"pref":"愛知","name":"岡崎市","empty":"12,690"},
{"pref":"愛知","name":"一宮市","empty":"16,920"},
{"pref":"愛知","name":"瀬戸市","empty":"7,090"},
{"pref":"愛知","name":"半田市","empty":"7,190"},
{"pref":"愛知","name":"春日井市","empty":"16,450"},
{"pref":"愛知","name":"豊川市","empty":"9,310"},
{"pref":"愛知","name":"津島市","empty":"3,700"},
{"pref":"愛知","name":"碧南市","empty":"3,070"},
{"pref":"愛知","name":"刈谷市","empty":"5,070"},
{"pref":"愛知","name":"豊田市","empty":"15,730"},
{"pref":"愛知","name":"安城市","empty":"5,350"},
{"pref":"愛知","name":"西尾市","empty":"7,320"},
{"pref":"愛知","name":"蒲郡市","empty":"4,260"},
{"pref":"愛知","name":"犬山市","empty":"3,830"},
{"pref":"愛知","name":"常滑市","empty":"3,660"},
{"pref":"愛知","name":"江南市","empty":"3,900"},
{"pref":"愛知","name":"小牧市","empty":"6,930"},
{"pref":"愛知","name":"稲沢市","empty":"6,340"},
{"pref":"愛知","name":"新城市","empty":"3,060"},
{"pref":"愛知","name":"東海市","empty":"4,670"},
{"pref":"愛知","name":"大府市","empty":"3,430"},
{"pref":"愛知","name":"知多市","empty":"4,150"},
{"pref":"愛知","name":"知立市","empty":"3,220"},
{"pref":"愛知","name":"尾張旭市","empty":"3,400"},
{"pref":"愛知","name":"高浜市","empty":"1,710"},
{"pref":"愛知","name":"岩倉市","empty":"2,330"},
{"pref":"愛知","name":"豊明市","empty":"3,020"},
{"pref":"愛知","name":"日進市","empty":"4,350"},
{"pref":"愛知","name":"田原市","empty":"1,700"},
{"pref":"愛知","name":"愛西市","empty":"2,320"},
{"pref":"愛知","name":"清須市","empty":"4,060"},
{"pref":"愛知","name":"北名古屋市","empty":"4,000"},
{"pref":"愛知","name":"弥富市","empty":"1,790"},
{"pref":"愛知","name":"みよし市","empty":"2,490"},
{"pref":"愛知","name":"あま市","empty":"5,110"},
{"pref":"愛知","name":"長久手市","empty":"2,630"},
{"pref":"三重","name":"津市","empty":"23,310"},
{"pref":"三重","name":"四日市市","empty":"18,120"},
{"pref":"三重","name":"伊勢市","empty":"8,990"},
{"pref":"三重","name":"松阪市","empty":"12,620"},
{"pref":"三重","name":"桑名市","empty":"6,730"},
{"pref":"三重","name":"鈴鹿市","empty":"9,460"},
{"pref":"三重","name":"名張市","empty":"5,050"},
{"pref":"三重","name":"尾鷲市","empty":"3,130"},
{"pref":"三重","name":"亀山市","empty":"2,900"},
{"pref":"三重","name":"鳥羽市","empty":"2,740"},
{"pref":"三重","name":"熊野市","empty":"3,670"},
{"pref":"三重","name":"いなべ市","empty":"2,380"},
{"pref":"三重","name":"志摩市","empty":"6,570"},
{"pref":"三重","name":"伊賀市","empty":"7,470"},
{"pref":"滋賀","name":"大津市","empty":"18,680"},
{"pref":"滋賀","name":"彦根市","empty":"9,590"},
{"pref":"滋賀","name":"長浜市","empty":"7,290"},
{"pref":"滋賀","name":"近江八幡市","empty":"4,050"},
{"pref":"滋賀","name":"草津市","empty":"7,140"},
{"pref":"滋賀","name":"守山市","empty":"3,270"},
{"pref":"滋賀","name":"栗東市","empty":"2,480"},
{"pref":"滋賀","name":"甲賀市","empty":"4,520"},
{"pref":"滋賀","name":"野洲市","empty":"1,980"},
{"pref":"滋賀","name":"湖南市","empty":"4,150"},
{"pref":"滋賀","name":"高島市","empty":"4,800"},
{"pref":"滋賀","name":"東近江市","empty":"6,560"},
{"pref":"滋賀","name":"米原市","empty":"2,090"},
{"pref":"京都","name":"京都市","empty":"106,000"},
{"pref":"京都","name":"福知山市","empty":"7,300"},
{"pref":"京都","name":"舞鶴市","empty":"7,300"},
{"pref":"京都","name":"綾部市","empty":"3,580"},
{"pref":"京都","name":"宇治市","empty":"8,280"},
{"pref":"京都","name":"宮津市","empty":"2,700"},
{"pref":"京都","name":"亀岡市","empty":"5,280"},
{"pref":"京都","name":"城陽市","empty":"2,900"},
{"pref":"京都","name":"向日市","empty":"2,280"},
{"pref":"京都","name":"長岡京市","empty":"3,380"},
{"pref":"京都","name":"八幡市","empty":"3,180"},
{"pref":"京都","name":"京田辺市","empty":"2,340"},
{"pref":"京都","name":"京丹後市","empty":"3,150"},
{"pref":"京都","name":"南丹市","empty":"3,210"},
{"pref":"京都","name":"木津川市","empty":"2,490"},
{"pref":"大阪","name":"大阪市","empty":"286,100"},
{"pref":"大阪","name":"堺市","empty":"54,800"},
{"pref":"大阪","name":"岸和田市","empty":"11,810"},
{"pref":"大阪","name":"豊中市","empty":"30,830"},
{"pref":"大阪","name":"池田市","empty":"6,660"},
{"pref":"大阪","name":"吹田市","empty":"38,710"},
{"pref":"大阪","name":"泉大津市","empty":"5,650"},
{"pref":"大阪","name":"高槻市","empty":"17,020"},
{"pref":"大阪","name":"貝塚市","empty":"5,610"},
{"pref":"大阪","name":"守口市","empty":"13,180"},
{"pref":"大阪","name":"枚方市","empty":"23,560"},
{"pref":"大阪","name":"茨木市","empty":"14,690"},
{"pref":"大阪","name":"八尾市","empty":"18,830"},
{"pref":"大阪","name":"泉佐野市","empty":"6,770"},
{"pref":"大阪","name":"富田林市","empty":"6,870"},
{"pref":"大阪","name":"寝屋川市","empty":"17,200"},
{"pref":"大阪","name":"河内長野市","empty":"5,180"},
{"pref":"大阪","name":"松原市","empty":"8,450"},
{"pref":"大阪","name":"大東市","empty":"8,660"},
{"pref":"大阪","name":"和泉市","empty":"9,270"},
{"pref":"大阪","name":"箕面市","empty":"9,060"},
{"pref":"大阪","name":"柏原市","empty":"5,480"},
{"pref":"大阪","name":"羽曳野市","empty":"8,520"},
{"pref":"大阪","name":"門真市","empty":"11,970"},
{"pref":"大阪","name":"摂津市","empty":"5,940"},
{"pref":"大阪","name":"高石市","empty":"4,190"},
{"pref":"大阪","name":"藤井寺市","empty":"4,450"},
{"pref":"大阪","name":"東大阪市","empty":"44,390"},
{"pref":"大阪","name":"泉南市","empty":"3,550"},
{"pref":"大阪","name":"四條畷市","empty":"3,630"},
{"pref":"大阪","name":"交野市","empty":"3,160"},
{"pref":"大阪","name":"大阪狭山市","empty":"2,940"},
{"pref":"大阪","name":"阪南市","empty":"3,600"},
{"pref":"兵庫","name":"神戸市","empty":"109,200"},
{"pref":"兵庫","name":"姫路市","empty":"37,660"},
{"pref":"兵庫","name":"尼崎市","empty":"37,280"},
{"pref":"兵庫","name":"明石市","empty":"18,500"},
{"pref":"兵庫","name":"西宮市","empty":"23,880"},
{"pref":"兵庫","name":"洲本市","empty":"5,760"},
{"pref":"兵庫","name":"芦屋市","empty":"5,370"},
{"pref":"兵庫","name":"伊丹市","empty":"9,460"},
{"pref":"兵庫","name":"相生市","empty":"3,000"},
{"pref":"兵庫","name":"豊岡市","empty":"5,850"},
{"pref":"兵庫","name":"加古川市","empty":"12,220"},
{"pref":"兵庫","name":"赤穂市","empty":"3,540"},
{"pref":"兵庫","name":"西脇市","empty":"3,040"},
{"pref":"兵庫","name":"宝塚市","empty":"11,620"},
{"pref":"兵庫","name":"三木市","empty":"4,050"},
{"pref":"兵庫","name":"高砂市","empty":"5,660"},
{"pref":"兵庫","name":"川西市","empty":"8,600"},
{"pref":"兵庫","name":"小野市","empty":"2,200"},
{"pref":"兵庫","name":"三田市","empty":"4,240"},
{"pref":"兵庫","name":"加西市","empty":"2,330"},
{"pref":"兵庫","name":"篠山市","empty":"2,960"},
{"pref":"兵庫","name":"養父市","empty":"2,390"},
{"pref":"兵庫","name":"丹波市","empty":"4,470"},
{"pref":"兵庫","name":"南あわじ市","empty":"3,950"},
{"pref":"兵庫","name":"朝来市","empty":"2,560"},
{"pref":"兵庫","name":"淡路市","empty":"5,980"},
{"pref":"兵庫","name":"宍粟市","empty":"2,680"},
{"pref":"兵庫","name":"加東市","empty":"4,460"},
{"pref":"兵庫","name":"たつの市","empty":"4,070"},
{"pref":"奈良","name":"奈良市","empty":"22,380"},
{"pref":"奈良","name":"大和高田市","empty":"7,360"},
{"pref":"奈良","name":"大和郡山市","empty":"4,880"},
{"pref":"奈良","name":"天理市","empty":"3,880"},
{"pref":"奈良","name":"橿原市","empty":"8,730"},
{"pref":"奈良","name":"桜井市","empty":"4,000"},
{"pref":"奈良","name":"五條市","empty":"3,190"},
{"pref":"奈良","name":"御所市","empty":"2,850"},
{"pref":"奈良","name":"生駒市","empty":"5,160"},
{"pref":"奈良","name":"香芝市","empty":"2,560"},
{"pref":"奈良","name":"葛城市","empty":"1,380"},
{"pref":"奈良","name":"宇陀市","empty":"2,040"},
{"pref":"和歌山","name":"和歌山市","empty":"35,230"},
{"pref":"和歌山","name":"海南市","empty":"5,220"},
{"pref":"和歌山","name":"橋本市","empty":"4,170"},
{"pref":"和歌山","name":"有田市","empty":"2,160"},
{"pref":"和歌山","name":"御坊市","empty":"2,430"},
{"pref":"和歌山","name":"田辺市","empty":"8,500"},
{"pref":"和歌山","name":"新宮市","empty":"3,710"},
{"pref":"和歌山","name":"紀の川市","empty":"4,380"},
{"pref":"和歌山","name":"岩出市","empty":"2,970"},
{"pref":"鳥取","name":"鳥取市","empty":"13,630"},
{"pref":"鳥取","name":"米子市","empty":"11,770"},
{"pref":"鳥取","name":"倉吉市","empty":"3,590"},
{"pref":"鳥取","name":"境港市","empty":"2,580"},
{"pref":"島根","name":"松江市","empty":"12,830"},
{"pref":"島根","name":"浜田市","empty":"4,520"},
{"pref":"島根","name":"出雲市","empty":"7,450"},
{"pref":"島根","name":"益田市","empty":"3,640"},
{"pref":"島根","name":"大田市","empty":"4,370"},
{"pref":"島根","name":"安来市","empty":"2,130"},
{"pref":"島根","name":"江津市","empty":"2,750"},
{"pref":"島根","name":"雲南市","empty":"1,860"},
{"pref":"岡山","name":"岡山市","empty":"53,200"},
{"pref":"岡山","name":"倉敷市","empty":"26,040"},
{"pref":"岡山","name":"津山市","empty":"11,200"},
{"pref":"岡山","name":"玉野市","empty":"5,360"},
{"pref":"岡山","name":"笠岡市","empty":"5,400"},
{"pref":"岡山","name":"井原市","empty":"3,110"},
{"pref":"岡山","name":"総社市","empty":"3,220"},
{"pref":"岡山","name":"高梁市","empty":"3,460"},
{"pref":"岡山","name":"新見市","empty":"3,190"},
{"pref":"岡山","name":"備前市","empty":"3,830"},
{"pref":"岡山","name":"瀬戸内市","empty":"2,840"},
{"pref":"岡山","name":"赤磐市","empty":"3,090"},
{"pref":"岡山","name":"真庭市","empty":"3,900"},
{"pref":"岡山","name":"美作市","empty":"4,100"},
{"pref":"岡山","name":"浅口市","empty":"1,810"},
{"pref":"広島","name":"広島市","empty":"73,000"},
{"pref":"広島","name":"呉市","empty":"27,960"},
{"pref":"広島","name":"竹原市","empty":"3,400"},
{"pref":"広島","name":"三原市","empty":"10,010"},
{"pref":"広島","name":"尾道市","empty":"14,320"},
{"pref":"広島","name":"福山市","empty":"30,110"},
{"pref":"広島","name":"府中市","empty":"3,370"},
{"pref":"広島","name":"三次市","empty":"4,680"},
{"pref":"広島","name":"庄原市","empty":"4,570"},
{"pref":"広島","name":"大竹市","empty":"2,390"},
{"pref":"広島","name":"東広島市","empty":"12,730"},
{"pref":"広島","name":"廿日市市","empty":"6,750"},
{"pref":"広島","name":"安芸高田市","empty":"3,220"},
{"pref":"広島","name":"江田島市","empty":"4,000"},
{"pref":"山口","name":"下関市","empty":"26,230"},
{"pref":"山口","name":"宇部市","empty":"14,030"},
{"pref":"山口","name":"山口市","empty":"17,860"},
{"pref":"山口","name":"萩市","empty":"5,430"},
{"pref":"山口","name":"防府市","empty":"8,270"},
{"pref":"山口","name":"下松市","empty":"3,940"},
{"pref":"山口","name":"岩国市","empty":"13,710"},
{"pref":"山口","name":"光市","empty":"3,510"},
{"pref":"山口","name":"長門市","empty":"3,170"},
{"pref":"山口","name":"柳井市","empty":"4,350"},
{"pref":"山口","name":"美祢市","empty":"2,440"},
{"pref":"山口","name":"周南市","empty":"11,150"},
{"pref":"山口","name":"山陽小野田市","empty":"4,630"},
{"pref":"徳島","name":"徳島市","empty":"24,270"},
{"pref":"徳島","name":"鳴門市","empty":"6,750"},
{"pref":"徳島","name":"小松島市","empty":"3,810"},
{"pref":"徳島","name":"阿南市","empty":"5,300"},
{"pref":"徳島","name":"吉野川市","empty":"3,630"},
{"pref":"徳島","name":"阿波市","empty":"2,760"},
{"pref":"徳島","name":"美馬市","empty":"4,090"},
{"pref":"徳島","name":"三好市","empty":"4,090"},
{"pref":"香川","name":"高松市","empty":"37,800"},
{"pref":"香川","name":"丸亀市","empty":"9,590"},
{"pref":"香川","name":"坂出市","empty":"5,850"},
{"pref":"香川","name":"善通寺市","empty":"3,420"},
{"pref":"香川","name":"観音寺市","empty":"4,550"},
{"pref":"香川","name":"さぬき市","empty":"4,440"},
{"pref":"香川","name":"東かがわ市","empty":"3,240"},
{"pref":"香川","name":"三豊市","empty":"4,260"},
{"pref":"愛媛","name":"松山市","empty":"39,340"},
{"pref":"愛媛","name":"今治市","empty":"20,060"},
{"pref":"愛媛","name":"宇和島市","empty":"8,450"},
{"pref":"愛媛","name":"八幡浜市","empty":"4,160"},
{"pref":"愛媛","name":"新居浜市","empty":"10,200"},
{"pref":"愛媛","name":"西条市","empty":"9,820"},
{"pref":"愛媛","name":"大洲市","empty":"4,960"},
{"pref":"愛媛","name":"伊予市","empty":"2,150"},
{"pref":"愛媛","name":"四国中央市","empty":"7,680"},
{"pref":"愛媛","name":"西予市","empty":"4,640"},
{"pref":"愛媛","name":"東温市","empty":"2,380"},
{"pref":"高知","name":"高知市","empty":"29,900"},
{"pref":"高知","name":"室戸市","empty":"2,800"},
{"pref":"高知","name":"安芸市","empty":"2,270"},
{"pref":"高知","name":"南国市","empty":"3,270"},
{"pref":"高知","name":"土佐市","empty":"2,060"},
{"pref":"高知","name":"須崎市","empty":"2,160"},
{"pref":"高知","name":"宿毛市","empty":"2,090"},
{"pref":"高知","name":"土佐清水市","empty":"2,670"},
{"pref":"高知","name":"四万十市","empty":"3,300"},
{"pref":"高知","name":"香南市","empty":"2,460"},
{"pref":"高知","name":"香美市","empty":"2,790"},
{"pref":"福岡","name":"北九州市","empty":"79,300"},
{"pref":"福岡","name":"福岡市","empty":"94,200"},
{"pref":"福岡","name":"大牟田市","empty":"10,920"},
{"pref":"福岡","name":"久留米市","empty":"20,910"},
{"pref":"福岡","name":"直方市","empty":"4,280"},
{"pref":"福岡","name":"飯塚市","empty":"13,590"},
{"pref":"福岡","name":"田川市","empty":"4,940"},
{"pref":"福岡","name":"柳川市","empty":"3,430"},
{"pref":"福岡","name":"八女市","empty":"3,960"},
{"pref":"福岡","name":"筑後市","empty":"2,270"},
{"pref":"福岡","name":"大川市","empty":"1,770"},
{"pref":"福岡","name":"行橋市","empty":"4,510"},
{"pref":"福岡","name":"豊前市","empty":"2,230"},
{"pref":"福岡","name":"中間市","empty":"2,630"},
{"pref":"福岡","name":"小郡市","empty":"2,340"},
{"pref":"福岡","name":"筑紫野市","empty":"4,080"},
{"pref":"福岡","name":"春日市","empty":"5,490"},
{"pref":"福岡","name":"大野城市","empty":"3,440"},
{"pref":"福岡","name":"宗像市","empty":"4,630"},
{"pref":"福岡","name":"太宰府市","empty":"3,010"},
{"pref":"福岡","name":"古賀市","empty":"2,260"},
{"pref":"福岡","name":"福津市","empty":"3,020"},
{"pref":"福岡","name":"うきは市","empty":"1,750"},
{"pref":"福岡","name":"宮若市","empty":"2,420"},
{"pref":"福岡","name":"嘉麻市","empty":"3,670"},
{"pref":"福岡","name":"朝倉市","empty":"3,200"},
{"pref":"福岡","name":"みやま市","empty":"1,810"},
{"pref":"福岡","name":"糸島市","empty":"4,370"},
{"pref":"福岡","name":"那珂川市","empty":"1,800"},
{"pref":"佐賀","name":"佐賀市","empty":"17,850"},
{"pref":"佐賀","name":"唐津市","empty":"8,020"},
{"pref":"佐賀","name":"鳥栖市","empty":"3,580"},
{"pref":"佐賀","name":"多久市","empty":"1,470"},
{"pref":"佐賀","name":"伊万里市","empty":"3,210"},
{"pref":"佐賀","name":"武雄市","empty":"2,620"},
{"pref":"佐賀","name":"鹿島市","empty":"1,460"},
{"pref":"佐賀","name":"小城市","empty":"2,250"},
{"pref":"佐賀","name":"嬉野市","empty":"1,760"},
{"pref":"佐賀","name":"神埼市","empty":"1,580"},
{"pref":"長崎","name":"長崎市","empty":"33,900"},
{"pref":"長崎","name":"佐世保市","empty":"20,590"},
{"pref":"長崎","name":"島原市","empty":"3,380"},
{"pref":"長崎","name":"諫早市","empty":"6,950"},
{"pref":"長崎","name":"大村市","empty":"4,590"},
{"pref":"長崎","name":"平戸市","empty":"2,590"},
{"pref":"長崎","name":"松浦市","empty":"2,080"},
{"pref":"長崎","name":"対馬市","empty":"3,000"},
{"pref":"長崎","name":"壱岐市","empty":"1,490"},
{"pref":"長崎","name":"五島市","empty":"5,150"},
{"pref":"長崎","name":"西海市","empty":"2,600"},
{"pref":"長崎","name":"雲仙市","empty":"2,540"},
{"pref":"長崎","name":"南島原市","empty":"3,330"},
{"pref":"熊本","name":"熊本市","empty":"43,500"},
{"pref":"熊本","name":"八代市","empty":"8,690"},
{"pref":"熊本","name":"人吉市","empty":"3,280"},
{"pref":"熊本","name":"荒尾市","empty":"3,840"},
{"pref":"熊本","name":"水俣市","empty":"2,580"},
{"pref":"熊本","name":"玉名市","empty":"4,410"},
{"pref":"熊本","name":"山鹿市","empty":"4,010"},
{"pref":"熊本","name":"菊池市","empty":"2,610"},
{"pref":"熊本","name":"宇土市","empty":"2,060"},
{"pref":"熊本","name":"上天草市","empty":"2,920"},
{"pref":"熊本","name":"宇城市","empty":"3,190"},
{"pref":"熊本","name":"阿蘇市","empty":"1,980"},
{"pref":"熊本","name":"天草市","empty":"9,000"},
{"pref":"熊本","name":"合志市","empty":"1,810"},
{"pref":"大分","name":"大分市","empty":"27,100"},
{"pref":"大分","name":"別府市","empty":"12,640"},
{"pref":"大分","name":"中津市","empty":"7,810"},
{"pref":"大分","name":"日田市","empty":"5,170"},
{"pref":"大分","name":"佐伯市","empty":"6,800"},
{"pref":"大分","name":"臼杵市","empty":"3,270"},
{"pref":"大分","name":"津久見市","empty":"1,850"},
{"pref":"大分","name":"竹田市","empty":"3,150"},
{"pref":"大分","name":"豊後高田市","empty":"2,480"},
{"pref":"大分","name":"杵築市","empty":"3,850"},
{"pref":"大分","name":"宇佐市","empty":"7,210"},
{"pref":"大分","name":"豊後大野市","empty":"3,380"},
{"pref":"大分","name":"由布市","empty":"4,430"},
{"pref":"大分","name":"国東市","empty":"4,440"},
{"pref":"宮崎","name":"宮崎市","empty":"26,190"},
{"pref":"宮崎","name":"都城市","empty":"16,670"},
{"pref":"宮崎","name":"延岡市","empty":"8,510"},
{"pref":"宮崎","name":"日南市","empty":"5,100"},
{"pref":"宮崎","name":"小林市","empty":"4,060"},
{"pref":"宮崎","name":"日向市","empty":"3,720"},
{"pref":"宮崎","name":"串間市","empty":"2,330"},
{"pref":"宮崎","name":"西都市","empty":"2,430"},
{"pref":"宮崎","name":"えびの市","empty":"2,870"},
{"pref":"鹿児島","name":"鹿児島市","empty":"47,580"},
{"pref":"鹿児島","name":"鹿屋市","empty":"9,630"},
{"pref":"鹿児島","name":"枕崎市","empty":"2,220"},
{"pref":"鹿児島","name":"阿久根市","empty":"2,620"},
{"pref":"鹿児島","name":"出水市","empty":"5,600"},
{"pref":"鹿児島","name":"指宿市","empty":"5,390"},
{"pref":"鹿児島","name":"西之表市","empty":"1,240"},
{"pref":"鹿児島","name":"垂水市","empty":"2,180"},
{"pref":"鹿児島","name":"薩摩川内市","empty":"11,290"},
{"pref":"鹿児島","name":"日置市","empty":"5,180"},
{"pref":"鹿児島","name":"曽於市","empty":"4,760"},
{"pref":"鹿児島","name":"霧島市","empty":"14,470"},
{"pref":"鹿児島","name":"いちき串木野市","empty":"2,700"},
{"pref":"鹿児島","name":"南さつま市","empty":"5,320"},
{"pref":"鹿児島","name":"志布志市","empty":"4,740"},
{"pref":"鹿児島","name":"奄美市","empty":"4,310"},
{"pref":"鹿児島","name":"南九州市","empty":"4,550"},
{"pref":"鹿児島","name":"伊佐市","empty":"4,140"},
{"pref":"鹿児島","name":"姶良市","empty":"6,410"},
{"pref":"沖縄","name":"那覇市","empty":"16,060"},
{"pref":"沖縄","name":"宜野湾市","empty":"4,050"},
{"pref":"沖縄","name":"石垣市","empty":"2,420"},
{"pref":"沖縄","name":"浦添市","empty":"4,180"},
{"pref":"沖縄","name":"名護市","empty":"4,920"},
{"pref":"沖縄","name":"糸満市","empty":"2,950"},
{"pref":"沖縄","name":"沖縄市","empty":"5,190"},
{"pref":"沖縄","name":"豊見城市","empty":"1,280"},
{"pref":"沖縄","name":"うるま市","empty":"4,760"},
{"pref":"沖縄","name":"宮古島市","empty":"3,500"},
{"pref":"沖縄","name":"南城市","empty":"2,490"}
]
